MANIFEST.in
Makefile
README.rst
requirements.txt
setup.py
bin/emu
bin/emu-clean
bin/emu-init
bin/emu-log
bin/emu-monitor
bin/emu-prune
bin/emu-pull
bin/emu-push
bin/emu-sink
emu/__init__.py
emu/cli.py
emu/io.py
emu/lockfile.py
emu/monitor.py
emu.egg-info/PKG-INFO
emu.egg-info/SOURCES.txt
emu.egg-info/dependency_links.txt
emu.egg-info/not-zip-safe
emu.egg-info/requires.txt
emu.egg-info/top_level.txt
emu/static/site.js
emu/static/styles.css
emu/templates/timeline.html
emu/templates/sink-templates/config
emu/templates/source-templates/config
emu/templates/source-templates/excludes
emu/templates/source-templates/hooks/exec/log.error.sample
emu/templates/source-templates/hooks/exec/mount-remote.post.sample
emu/templates/source-templates/hooks/exec/mount-remote.pre.sample
emu/templates/source-templates/hooks/push/email-report.post.sample
emu/templates/source-templates/hooks/push/email.error.sample
emu/templates/source-templates/hooks/push/log-start.pre.sample
emu/test/__init__.py
emu/test/test_emu.py
emu/test/test_io.py
man/emu-clean.1
man/emu-init.1
man/emu-log.1
man/emu-prune.1
man/emu-pull.1
man/emu-push.1
man/emu-sink.1
man/emu.1