Metadata-Version: 1.0
Name: emu
Version: 0.3.0
Summary: Fast, incremental, rotating backups
Home-page: https://github.com/ChrisCummins/emu
Author: Chris Cummins
Author-email: chrisc.101@gmail.com
License: GNU GPL v3
Platform: UNKNOWN
